slitherin/__init__.py
slitherin/cli.py
slitherin/consts.py
slitherin/napalm.py
slitherin/__pycache__/__init__.cpython-311.pyc
slitherin/__pycache__/cli.cpython-311.pyc
slitherin/__pycache__/consts.cpython-311.pyc
slitherin/detectors/__init__.py
slitherin/detectors/before_token_transfer.py
slitherin/detectors/call_forward_to_protected.py
slitherin/detectors/double_entry_token_possibility.py
slitherin/detectors/dubious_typecast.py
slitherin/detectors/ecrecover.py
slitherin/detectors/event_setter.py
slitherin/detectors/falsy_only_eoa_modifier.py
slitherin/detectors/for_continue_increment.py
slitherin/detectors/inconsistent_nonreentrant.py
slitherin/detectors/magic_number.py
slitherin/detectors/multiple_storage_read.py
slitherin/detectors/nft_approve_warning.py
slitherin/detectors/potential_arith_overflow.py
slitherin/detectors/price_manipulation.py
slitherin/detectors/public_vs_external.py
slitherin/detectors/read_only_reentrancy.py
slitherin/detectors/strange_setter.py
slitherin/detectors/timelock_controller.py
slitherin/detectors/token_fallback.py
slitherin/detectors/tx_gasprice_warning.py
slitherin/detectors/uni_v2.py
slitherin/detectors/unprotected_initialize.py
slitherin/detectors/unprotected_setter.py
slitherin/detectors/__pycache__/__init__.cpython-311.pyc
slitherin/detectors/__pycache__/before_token_transfer.cpython-311.pyc
slitherin/detectors/__pycache__/call_forward_to_protected.cpython-311.pyc
slitherin/detectors/__pycache__/double_entry_token_possibility.cpython-311.pyc
slitherin/detectors/__pycache__/dubious_typecast.cpython-311.pyc
slitherin/detectors/__pycache__/ecrecover.cpython-311.pyc
slitherin/detectors/__pycache__/event_setter.cpython-311.pyc
slitherin/detectors/__pycache__/falsy_only_eoa_modifier.cpython-311.pyc
slitherin/detectors/__pycache__/for_continue_increment.cpython-311.pyc
slitherin/detectors/__pycache__/inconsistent_nonreentrant.cpython-311.pyc
slitherin/detectors/__pycache__/magic_number.cpython-311.pyc
slitherin-0.7.2.dist-info/LICENSE.txt
slitherin-0.7.2.dist-info/METADATA
slitherin-0.7.2.dist-info/WHEEL
slitherin-0.7.2.dist-info/entry_points.txt
slitherin-0.7.2.dist-info/top_level.txt
slitherin-0.7.2.dist-info/RECORD
