Metadata-Version: 2.1
Name: slitherin
Version: 0.7.2
Summary: Pessimistic security Slither detectors
Home-page: https://github.com/pessimistic-io/slitherin
Author: Pessimistic.io
Author-email: info@pessimistic.io
License: AGPL-3.0
Classifier: Development Status :: 3 - Alpha
Classifier: Programming Language :: Python
Classifier: License :: OSI Approved :: Apache Software License
Classifier: Topic :: Software Development :: Libraries
Requires-Python: >=3.8
License-File: LICENSE.txt
Requires-Dist: slither-analyzer >=0.10.0
